LICENSE
MANIFEST.in
README.rst
setup.py
esdc_api/__init__.py
esdc_api/client.py
esdc_api/exceptions.py
esdc_api/response.py
esdc_api.egg-info/PKG-INFO
esdc_api.egg-info/SOURCES.txt
esdc_api.egg-info/dependency_links.txt
esdc_api.egg-info/top_level.txt