Metadata-Version: 1.1
Name: esdc-api
Version: 2.0
Summary: Danube Cloud API Python Library
Home-page: https://github.com/erigones/esdc-api/
Author: Erigones
Author-email: erigones [at] erigones.com
License: BSD
Platform: any
Classifier: Environment :: Web Environment
Classifier: Environment :: Console
Classifier: Environment :: Plugins
Classifier: Intended Audience :: System Administrators
Classifier: Intended Audience :: Developers
Classifier: License :: OSI Approved :: BSD License
Classifier: Programming Language :: Python
Classifier: Programming Language :: Python :: 2
Classifier: Programming Language :: Python :: 3
Classifier: Development Status :: 5 - Production/Stable
Classifier: Topic :: Software Development :: Libraries
Classifier: Topic :: Software Development :: Libraries :: Python Modules
Requires: requests
